Metadata-Version: 2.2
Name: seiz_eeg
Version: 0.4.3
Summary: Data loading and preprocessing of EEG scans for seizure-related ML tasks
Author-email: William Cappelletti <william.cappelletti@epfl.ch>
License: BSD-3-Clause
Project-URL: Homepage, https://github.com/LTS4/seizure_eeg
Project-URL: Issues, https://github.com/LTS4/seizure_eeg/issues
Keywords: seizure analysis,machine learning
Classifier: Programming Language :: Python :: 3
Classifier: Development Status :: 3 - Alpha
Classifier: License :: OSI Approved :: BSD License
Classifier: Operating System :: OS Independent
Classifier: Natural Language :: English
Classifier: Topic :: Scientific/Engineering :: Artificial Intelligence
Classifier: Topic :: Scientific/Engineering :: Medical Science Apps.
Requires-Python: >=3.10
License-File: LICENSE
Requires-Dist: click
Requires-Dist: numpy
Requires-Dist: pandas
Requires-Dist: pandera
Requires-Dist: pyarrow
Requires-Dist: pyEDFlib
Requires-Dist: scipy
Requires-Dist: omegaconf
Requires-Dist: pexpect
Requires-Dist: tqdm
Provides-Extra: dev
Requires-Dist: pylint; extra == "dev"
Requires-Dist: pytest; extra == "dev"
Requires-Dist: black; extra == "dev"
Requires-Dist: isort; extra == "dev"
Provides-Extra: build
Requires-Dist: build; extra == "build"
Requires-Dist: twine; extra == "build"
